README.rst
setup.cfg
setup.py
PyUPS.egg-info/PKG-INFO
PyUPS.egg-info/SOURCES.txt
PyUPS.egg-info/dependency_links.txt
PyUPS.egg-info/requires.txt
PyUPS.egg-info/top_level.txt
ups/__init__.py
ups/address_validation.py
ups/base.py
ups/rating_package.py
ups/shipping_package.py
ups/time_in_transit.py
ups/worldship_api.py
ups/tests/__init__.py
ups/tests/helper.py
ups/tests/test_address_validation.py
ups/tests/test_rating_package.py
ups/tests/test_shipping_package_gb_xx.py
ups/tests/test_time_in_transit.py
ups/tests/test_worldship_xml.py