Metadata-Version: 1.0
Name: PyUPS
Version: 0.6.2
Summary: Python client to UPS® Shipping Webservice API
Home-page: http://openlabs.co.in
Author: Openlabs Technologies & Consulting (P) LTD
Author-email: info@openlabs.co.in
License: AGPL
Keywords: UPS®,Shipping,United Parcel Service of America®
Platform: UNKNOWN
